README.md
setup.py
hyhmath/__init__.py
hyhmath/add.py
hyhmath.egg-info/PKG-INFO
hyhmath.egg-info/SOURCES.txt
hyhmath.egg-info/dependency_links.txt
hyhmath.egg-info/top_level.txt
hyhmath/adv/__init__.py
hyhmath/adv/sqrt.py