Metadata-Version: 1.0
Name: hyhmath
Version: 0.1
Summary: A pkg test
Home-page: https://github.com/huoyinghui
Author: hyhlinux
Author-email: django_hyh@163.com
License: UNKNOWN
Platform: UNKNOWN
